mess/__init__.py
mess/autograd_integrals.py
mess/basis.py
mess/binom_factor_table.py
mess/hamiltonian.py
mess/integrals.py
mess/interop.py
mess/mesh.py
mess/numerics.py
mess/orbital.py
mess/orthnorm.py
mess/package_utils.py
mess/plot.py
mess/primitive.py
mess/scf.py
mess/special.py
mess/structure.py
mess/types.py
mess/units.py
mess/xcfunctional.py
mess/zeropad_integrals.py
mess_jax-0.1.2.dist-info/LICENSE
mess_jax-0.1.2.dist-info/METADATA
mess_jax-0.1.2.dist-info/WHEEL
mess_jax-0.1.2.dist-info/top_level.txt
mess_jax-0.1.2.dist-info/RECORD
