Metadata-Version: 2.1
Name: mess-jax
Version: 0.1.2
Summary: MESS: Modern Electronic Structure Simulations
Author-email: Hatem Helal <hatem@valencelabs.com>
License: MIT License
Project-URL: Website, https://github.com/valence-labs/mess
Project-URL: Source Code, https://github.com/valence-labs/mess
Project-URL: Bug Tracker, https://github.com/valence-labs/mess/issues
Project-URL: Documentation, https://valence-labs.github.io/mess/
Classifier: Development Status :: 3 - Alpha
Classifier: Intended Audience :: Developers
Classifier: Topic :: Scientific/Engineering
Classifier: License :: OSI Approved :: MIT License
Classifier: Programming Language :: Python :: 3
Requires-Python: >=3.11
License-File: LICENSE
Requires-Dist: equinox
Requires-Dist: jax[cpu]
Requires-Dist: jaxtyping
Requires-Dist: more-itertools
Requires-Dist: optax
Requires-Dist: optimistix
Requires-Dist: pandas
Requires-Dist: periodictable
Requires-Dist: pyarrow
Requires-Dist: pyscf
Requires-Dist: py3Dmol
Requires-Dist: basis-set-exchange
Requires-Dist: sympy
Requires-Dist: importlib-resources
Provides-Extra: dev
Requires-Dist: jupyter-book; extra == "dev"
Requires-Dist: tqdm; extra == "dev"
Requires-Dist: ipywidgets; extra == "dev"
Requires-Dist: pytest; extra == "dev"
Requires-Dist: pytest-benchmark; extra == "dev"
Requires-Dist: pre-commit; extra == "dev"
Requires-Dist: ruff; extra == "dev"
Requires-Dist: mdformat-gfm; extra == "dev"
Requires-Dist: seaborn; extra == "dev"
